[
  {
    "id": "L0-1001",
    "tw": "我",
    "pinyin": "wǒ",
    "zhuyin": "ㄨㄛˇ",
    "ja": "私",
    "pos": "N"
  },
  {
    "id": "L0-1002",
    "tw": "你",
    "pinyin": "nǐ",
    "zhuyin": "ㄋㄧˇ",
    "ja": "あなた",
    "pos": "N"
  },
  {
    "id": "L0-1003",
    "tw": "他",
    "pinyin": "tā",
    "zhuyin": "ㄊㄚ",
    "ja": "彼",
    "pos": "N"
  },
  {
    "id": "L0-1004",
    "tw": "我們",
    "pinyin": "wǒmen",
    "zhuyin": "ㄨㄛˇ ㄇㄣ˙",
    "ja": "私たち",
    "pos": "N"
  },
  {
    "id": "L0-1005",
    "tw": "你們",
    "pinyin": "nǐmen",
    "zhuyin": "ㄋㄧˇ ㄇㄣ˙",
    "ja": "あなたたち",
    "pos": "N"
  },
  {
    "id": "L0-1006",
    "tw": "他們",
    "pinyin": "tāmen",
    "zhuyin": "ㄊㄚ ㄇㄣ˙",
    "ja": "彼ら",
    "pos": "N"
  },
  {
    "id": "L0-1007",
    "tw": "您",
    "pinyin": "nín",
    "zhuyin": "ㄋㄧㄣˊ",
    "ja": "あなた様",
    "pos": "N"
  },
  {
    "id": "L0-1008",
    "tw": "誰",
    "pinyin": "shéi",
    "zhuyin": "ㄕㄟˊ",
    "ja": "誰",
    "pos": "N"
  },
  {
    "id": "L0-1009",
    "tw": "姓名",
    "pinyin": "xìngmíng",
    "zhuyin": "ㄒㄧㄥˋ ㄇㄧㄥˊ",
    "ja": "氏名",
    "pos": "N"
  },
  {
    "id": "L0-1010",
    "tw": "人",
    "pinyin": "rén",
    "zhuyin": "ㄖㄣˊ",
    "ja": "人",
    "pos": "N"
  },
  {
    "id": "L0-1011",
    "tw": "國",
    "pinyin": "guó",
    "zhuyin": "ㄍㄨㄛˊ",
    "ja": "国",
    "pos": "N"
  },
  {
    "id": "L0-1012",
    "tw": "中國",
    "pinyin": "Zhōngguó",
    "zhuyin": "ㄓㄨㄥ ㄍㄨㄛˊ",
    "ja": "中国",
    "pos": "N"
  },
  {
    "id": "L0-1013",
    "tw": "美國",
    "pinyin": "Měiguó",
    "zhuyin": "ㄇㄟˇ ㄍㄨㄛˊ",
    "ja": "アメリカ",
    "pos": "N"
  },
  {
    "id": "L0-1014",
    "tw": "日本",
    "pinyin": "Rìběn",
    "zhuyin": "ㄖˋ ㄅㄣˇ",
    "ja": "日本",
    "pos": "N"
  },
  {
    "id": "L0-1015",
    "tw": "台灣",
    "pinyin": "Táiwān",
    "zhuyin": "ㄊㄞˊ ㄨㄢ",
    "ja": "台湾",
    "pos": "N"
  },
  {
    "id": "L0-1016",
    "tw": "名字",
    "pinyin": "míngzi",
    "zhuyin": "ㄇㄧㄥˊ ㄗ˙",
    "ja": "名前",
    "pos": "N"
  },
  {
    "id": "L0-1017",
    "tw": "家",
    "pinyin": "jiā",
    "zhuyin": "ㄐㄧㄚ",
    "ja": "家",
    "pos": "N"
  },
  {
    "id": "L0-1018",
    "tw": "電話",
    "pinyin": "diànhuà",
    "zhuyin": "ㄉㄧㄢˋ ㄏㄨㄚˋ",
    "ja": "電話",
    "pos": "N"
  },
  {
    "id": "L0-1019",
    "tw": "時間",
    "pinyin": "shíjiān",
    "zhuyin": "ㄕˊ ㄐㄧㄢ",
    "ja": "時間",
    "pos": "N"
  },
  {
    "id": "L0-1020",
    "tw": "小時",
    "pinyin": "xiǎoshí",
    "zhuyin": "ㄒㄧㄠˇ ㄕˊ",
    "ja": "時間、アワー",
    "pos": "N"
  },
  {
    "id": "L0-1021",
    "tw": "現在",
    "pinyin": "xiànzài",
    "zhuyin": "ㄒㄧㄢˋ ㄗㄞˋ",
    "ja": "今",
    "pos": "N"
  },
  {
    "id": "L0-1022",
    "tw": "今年",
    "pinyin": "jīnnián",
    "zhuyin": "ㄐㄧㄣ ㄋㄧㄢˊ",
    "ja": "今年",
    "pos": "N"
  },
  {
    "id": "L0-1023",
    "tw": "今天",
    "pinyin": "jīntiān",
    "zhuyin": "ㄐㄧㄣ ㄊㄧㄢ",
    "ja": "今日",
    "pos": "N"
  },
  {
    "id": "L0-1024",
    "tw": "明天",
    "pinyin": "míngtiān",
    "zhuyin": "ㄇㄧㄥˊ ㄊㄧㄢ",
    "ja": "明日",
    "pos": "N"
  },
  {
    "id": "L0-1025",
    "tw": "昨天",
    "pinyin": "zuótiān",
    "zhuyin": "ㄗㄨㄛˊ ㄊㄧㄢ",
    "ja": "昨日",
    "pos": "N"
  },
  {
    "id": "L0-1026",
    "tw": "早上",
    "pinyin": "zǎoshàng",
    "zhuyin": "ㄗㄠˇ ㄕㄤˋ",
    "ja": "朝",
    "pos": "N"
  },
  {
    "id": "L0-1027",
    "tw": "上午",
    "pinyin": "shàngwǔ",
    "zhuyin": "ㄕㄤˋ ㄨˇ",
    "ja": "午前",
    "pos": "N"
  },
  {
    "id": "L0-1028",
    "tw": "中午",
    "pinyin": "zhōngwǔ",
    "zhuyin": "ㄓㄨㄥ ㄨˇ",
    "ja": "正午",
    "pos": "N"
  },
  {
    "id": "L0-1029",
    "tw": "下午",
    "pinyin": "xiàwǔ",
    "zhuyin": "ㄒㄧㄚˋ ㄨˇ",
    "ja": "午後",
    "pos": "N"
  },
  {
    "id": "L0-1030",
    "tw": "晚上",
    "pinyin": "wǎnshàng",
    "zhuyin": "ㄨㄢˇ ㄕㄤˋ",
    "ja": "夜",
    "pos": "N"
  },
  {
    "id": "L0-1031",
    "tw": "一",
    "pinyin": "yī",
    "zhuyin": "ㄧ",
    "ja": "一、いち",
    "pos": "N"
  },
  {
    "id": "L0-1032",
    "tw": "二",
    "pinyin": "èr",
    "zhuyin": "ㄦˋ",
    "ja": "二、に",
    "pos": "N"
  },
  {
    "id": "L0-1033",
    "tw": "三",
    "pinyin": "sān",
    "zhuyin": "ㄙㄢ",
    "ja": "三、さん",
    "pos": "N"
  },
  {
    "id": "L0-1034",
    "tw": "四",
    "pinyin": "sì",
    "zhuyin": "ㄙˋ",
    "ja": "四、よん",
    "pos": "N"
  },
  {
    "id": "L0-1035",
    "tw": "五",
    "pinyin": "wǔ",
    "zhuyin": "ㄨˇ",
    "ja": "五、ご",
    "pos": "N"
  },
  {
    "id": "L0-1036",
    "tw": "六",
    "pinyin": "liù",
    "zhuyin": "ㄌㄧㄡˋ",
    "ja": "六、ろく",
    "pos": "N"
  },
  {
    "id": "L0-1037",
    "tw": "七",
    "pinyin": "qī",
    "zhuyin": "ㄑㄧ",
    "ja": "七、なな",
    "pos": "N"
  },
  {
    "id": "L0-1038",
    "tw": "八",
    "pinyin": "bā",
    "zhuyin": "ㄅㄚ",
    "ja": "八、はち",
    "pos": "N"
  },
  {
    "id": "L0-1039",
    "tw": "九",
    "pinyin": "jiǔ",
    "zhuyin": "ㄐㄧㄡˇ",
    "ja": "九、きゅう",
    "pos": "N"
  },
  {
    "id": "L0-1040",
    "tw": "十",
    "pinyin": "shí",
    "zhuyin": "ㄕˊ",
    "ja": "十、じゅう",
    "pos": "N"
  },
  {
    "id": "L0-1041",
    "tw": "兩",
    "pinyin": "liǎng",
    "zhuyin": "ㄌㄧㄤˇ",
    "ja": "二つ",
    "pos": "N"
  },
  {
    "id": "L0-1042",
    "tw": "時候",
    "pinyin": "shíhòu",
    "zhuyin": "ㄕˊ ㄏㄡˋ",
    "ja": "時、ころ",
    "pos": "N"
  },
  {
    "id": "L0-1043",
    "tw": "百",
    "pinyin": "bǎi",
    "zhuyin": "ㄅㄞˇ",
    "ja": "百",
    "pos": "N"
  },
  {
    "id": "L0-1044",
    "tw": "半",
    "pinyin": "bàn",
    "zhuyin": "ㄅㄢˋ",
    "ja": "半分",
    "pos": "N"
  },
  {
    "id": "L0-1045",
    "tw": "千",
    "pinyin": "qiān",
    "zhuyin": "ㄑㄧㄢ",
    "ja": "千",
    "pos": "N"
  },
  {
    "id": "L0-1046",
    "tw": "爸爸",
    "pinyin": "bàba",
    "zhuyin": "ㄅㄚˋ ㄅㄚ˙",
    "ja": "お父さん",
    "pos": "N"
  },
  {
    "id": "L0-1047",
    "tw": "媽媽",
    "pinyin": "māma",
    "zhuyin": "ㄇㄚ ㄇㄚ˙",
    "ja": "お母さん",
    "pos": "N"
  },
  {
    "id": "L0-1048",
    "tw": "哥哥",
    "pinyin": "gēge",
    "zhuyin": "ㄍㄜ ㄍㄜ˙",
    "ja": "兄",
    "pos": "N"
  },
  {
    "id": "L0-1049",
    "tw": "弟弟",
    "pinyin": "dìdi",
    "zhuyin": "ㄉㄧˋ ㄉㄧ˙",
    "ja": "弟",
    "pos": "N"
  },
  {
    "id": "L0-1050",
    "tw": "姊姊",
    "pinyin": "jiějie",
    "zhuyin": "ㄐㄧㄝˇ ㄐㄧㄝ˙",
    "ja": "姉",
    "pos": "N"
  },
  {
    "id": "L0-1051",
    "tw": "妹妹",
    "pinyin": "mèimei",
    "zhuyin": "ㄇㄟˋ ㄇㄟ˙",
    "ja": "妹",
    "pos": "N"
  },
  {
    "id": "L0-1052",
    "tw": "小孩",
    "pinyin": "xiǎohái",
    "zhuyin": "ㄒㄧㄠˇ ㄏㄞˊ",
    "ja": "子供",
    "pos": "N"
  },
  {
    "id": "L0-1053",
    "tw": "的",
    "pinyin": "de",
    "zhuyin": "ㄉㄜ˙",
    "ja": "の、修飾の助詞",
    "pos": "Ptc"
  },
  {
    "id": "L0-1054",
    "tw": "第",
    "pinyin": "dì",
    "zhuyin": "ㄉㄧˋ",
    "ja": "第",
    "pos": "Det"
  },
  {
    "id": "L0-1055",
    "tw": "分",
    "pinyin": "fēn",
    "zhuyin": "ㄈㄣ",
    "ja": "分、ふん",
    "pos": "M"
  },
  {
    "id": "L0-1056",
    "tw": "點",
    "pinyin": "diǎn",
    "zhuyin": "ㄉㄧㄢˇ",
    "ja": "時、じ",
    "pos": "M"
  },
  {
    "id": "L0-1057",
    "tw": "個",
    "pinyin": "ge",
    "zhuyin": "ㄍㄜ˙",
    "ja": "個、量詞",
    "pos": "M"
  },
  {
    "id": "L0-1058",
    "tw": "歲",
    "pinyin": "suì",
    "zhuyin": "ㄙㄨㄟˋ",
    "ja": "歳",
    "pos": "M"
  },
  {
    "id": "L0-1059",
    "tw": "年",
    "pinyin": "nián",
    "zhuyin": "ㄋㄧㄢˊ",
    "ja": "年",
    "pos": "M"
  },
  {
    "id": "L0-1060",
    "tw": "住",
    "pinyin": "zhù",
    "zhuyin": "ㄓㄨˋ",
    "ja": "住む",
    "pos": "V"
  },
  {
    "id": "L0-1061",
    "tw": "來",
    "pinyin": "lái",
    "zhuyin": "ㄌㄞˊ",
    "ja": "来る",
    "pos": "V"
  },
  {
    "id": "L0-1062",
    "tw": "是",
    "pinyin": "shì",
    "zhuyin": "ㄕˋ",
    "ja": "である",
    "pos": "Vst"
  },
  {
    "id": "L0-1063",
    "tw": "姓",
    "pinyin": "xìng",
    "zhuyin": "ㄒㄧㄥˋ",
    "ja": "という姓である",
    "pos": "Vst"
  },
  {
    "id": "L0-1064",
    "tw": "覺得",
    "pinyin": "juéde",
    "zhuyin": "ㄐㄩㄝˊ ㄉㄜ˙",
    "ja": "と思う、感じる",
    "pos": "Vst"
  },
  {
    "id": "L0-1065",
    "tw": "喜歡",
    "pinyin": "xǐhuān",
    "zhuyin": "ㄒㄧˇ ㄏㄨㄢ",
    "ja": "好きである",
    "pos": "Vst"
  },
  {
    "id": "L0-1066",
    "tw": "打電話",
    "pinyin": "dǎ diànhuà",
    "zhuyin": "ㄉㄚˇ ㄉㄧㄢˋ ㄏㄨㄚˋ",
    "ja": "電話をかける",
    "pos": "Vi"
  },
  {
    "id": "L0-1067",
    "tw": "漂亮",
    "pinyin": "piàoliàng",
    "zhuyin": "ㄆㄧㄠˋ ㄌㄧㄤˋ",
    "ja": "綺麗",
    "pos": "Vs"
  },
  {
    "id": "L0-1068",
    "tw": "高",
    "pinyin": "gāo",
    "zhuyin": "ㄍㄠ",
    "ja": "高い、背が高い",
    "pos": "Vs"
  },
  {
    "id": "L0-1069",
    "tw": "老",
    "pinyin": "lǎo",
    "zhuyin": "ㄌㄠˇ",
    "ja": "年をとっている",
    "pos": "Vs"
  },
  {
    "id": "L0-1070",
    "tw": "好",
    "pinyin": "hǎo",
    "zhuyin": "ㄏㄠˇ",
    "ja": "良い",
    "pos": "Adv"
  },
  {
    "id": "L0-1071",
    "tw": "很",
    "pinyin": "hěn",
    "zhuyin": "ㄏㄣˇ",
    "ja": "とても",
    "pos": "Adv"
  },
  {
    "id": "L0-1072",
    "tw": "真",
    "pinyin": "zhēn",
    "zhuyin": "ㄓㄣ",
    "ja": "本当に",
    "pos": "Adv"
  },
  {
    "id": "L0-1073",
    "tw": "電腦",
    "pinyin": "diànnǎo",
    "zhuyin": "ㄉㄧㄢˋ ㄋㄠˇ",
    "ja": "パソコン",
    "pos": "N"
  },
  {
    "id": "L0-1074",
    "tw": "老師",
    "pinyin": "lǎoshī",
    "zhuyin": "ㄌㄠˇ ㄕ",
    "ja": "先生",
    "pos": "N"
  },
  {
    "id": "L0-1075",
    "tw": "買",
    "pinyin": "mǎi",
    "zhuyin": "ㄇㄞˇ",
    "ja": "買う",
    "pos": "V"
  },
  {
    "id": "L0-1076",
    "tw": "忙",
    "pinyin": "máng",
    "zhuyin": "ㄇㄤˊ",
    "ja": "忙しい",
    "pos": "Vs"
  },
  {
    "id": "L0-1077",
    "tw": "學生",
    "pinyin": "xuéshēng",
    "zhuyin": "ㄒㄩㄝˊ ㄕㄥ",
    "ja": "学生",
    "pos": "N"
  },
  {
    "id": "L0-1078",
    "tw": "大學",
    "pinyin": "dàxué",
    "zhuyin": "ㄉㄚˋ ㄒㄩㄝˊ",
    "ja": "大学",
    "pos": "N"
  },
  {
    "id": "L0-1079",
    "tw": "學校",
    "pinyin": "xuéxiào",
    "zhuyin": "ㄒㄩㄝˊ ㄒㄧㄠˋ",
    "ja": "学校",
    "pos": "N"
  },
  {
    "id": "L0-1080",
    "tw": "中文",
    "pinyin": "Zhōngwén",
    "zhuyin": "ㄓㄨㄥ ㄨㄣˊ",
    "ja": "中国語",
    "pos": "N"
  },
  {
    "id": "L0-1081",
    "tw": "同學",
    "pinyin": "tóngxué",
    "zhuyin": "ㄊㄨㄥˊ ㄒㄩㄝˊ",
    "ja": "クラスメート",
    "pos": "N"
  },
  {
    "id": "L0-1082",
    "tw": "字",
    "pinyin": "zì",
    "zhuyin": "ㄗˋ",
    "ja": "字、文字",
    "pos": "N"
  },
  {
    "id": "L0-1083",
    "tw": "筆",
    "pinyin": "bǐ",
    "zhuyin": "ㄅㄧˇ",
    "ja": "ペン",
    "pos": "N"
  },
  {
    "id": "L0-1084",
    "tw": "學",
    "pinyin": "xué",
    "zhuyin": "ㄒㄩㄝˊ",
    "ja": "学ぶ",
    "pos": "V"
  },
  {
    "id": "L0-1085",
    "tw": "問",
    "pinyin": "wèn",
    "zhuyin": "ㄨㄣˋ",
    "ja": "尋ねる",
    "pos": "V"
  },
  {
    "id": "L0-1086",
    "tw": "說",
    "pinyin": "shuō",
    "zhuyin": "ㄕㄨㄛ",
    "ja": "言う、話す",
    "pos": "V"
  },
  {
    "id": "L0-1087",
    "tw": "寫",
    "pinyin": "xiě",
    "zhuyin": "ㄒㄧㄝˇ",
    "ja": "書く",
    "pos": "V"
  },
  {
    "id": "L0-1088",
    "tw": "聽",
    "pinyin": "tīng",
    "zhuyin": "ㄊㄧㄥ",
    "ja": "聞く",
    "pos": "V"
  },
  {
    "id": "L0-1089",
    "tw": "對",
    "pinyin": "duì",
    "zhuyin": "ㄉㄨㄟˋ",
    "ja": "正しい",
    "pos": "Vs"
  },
  {
    "id": "L0-1090",
    "tw": "能",
    "pinyin": "néng",
    "zhuyin": "ㄋㄥˊ",
    "ja": "できる",
    "pos": "Vaux"
  },
  {
    "id": "L0-1091",
    "tw": "可以",
    "pinyin": "kěyǐ",
    "zhuyin": "ㄎㄜˇ ㄧˇ",
    "ja": "してもよい",
    "pos": "Vaux"
  },
  {
    "id": "L0-1092",
    "tw": "上課",
    "pinyin": "shàngkè",
    "zhuyin": "ㄕㄤˋ ㄎㄜˋ",
    "ja": "授業に出る",
    "pos": "V-sep"
  },
  {
    "id": "L0-1093",
    "tw": "知道",
    "pinyin": "zhīdào",
    "zhuyin": "ㄓ ㄉㄠˋ",
    "ja": "知っている",
    "pos": "Vst"
  },
  {
    "id": "L0-1094",
    "tw": "電視",
    "pinyin": "diànshì",
    "zhuyin": "ㄉㄧㄢˋ ㄕˋ",
    "ja": "テレビ",
    "pos": "N"
  },
  {
    "id": "L0-1095",
    "tw": "水",
    "pinyin": "shuǐ",
    "zhuyin": "ㄕㄨㄟˇ",
    "ja": "水",
    "pos": "N"
  },
  {
    "id": "L0-1096",
    "tw": "久",
    "pinyin": "jiǔ",
    "zhuyin": "ㄐㄧㄡˇ",
    "ja": "長い時間",
    "pos": "Vs-pred"
  },
  {
    "id": "L0-1097",
    "tw": "早",
    "pinyin": "zǎo",
    "zhuyin": "ㄗㄠˇ",
    "ja": "早い",
    "pos": "Vs"
  },
  {
    "id": "L0-1098",
    "tw": "再",
    "pinyin": "zài",
    "zhuyin": "ㄗㄞˋ",
    "ja": "再び、もう一度",
    "pos": "Adv"
  },
  {
    "id": "L0-1099",
    "tw": "書",
    "pinyin": "shū",
    "zhuyin": "ㄕㄨ",
    "ja": "本",
    "pos": "N"
  },
  {
    "id": "L0-1100",
    "tw": "電影",
    "pinyin": "diànyǐng",
    "zhuyin": "ㄉㄧㄢˋ ㄧㄥˇ",
    "ja": "映画",
    "pos": "N"
  },
  {
    "id": "L0-1101",
    "tw": "以前",
    "pinyin": "yǐqián",
    "zhuyin": "ㄧˇ ㄑㄧㄢˊ",
    "ja": "以前",
    "pos": "N"
  },
  {
    "id": "L0-1102",
    "tw": "以後",
    "pinyin": "yǐhòu",
    "zhuyin": "ㄧˇ ㄏㄡˋ",
    "ja": "以後",
    "pos": "N"
  },
  {
    "id": "L0-1103",
    "tw": "走",
    "pinyin": "zǒu",
    "zhuyin": "ㄗㄡˇ",
    "ja": "歩く、行く",
    "pos": "V"
  },
  {
    "id": "L0-1104",
    "tw": "等",
    "pinyin": "děng",
    "zhuyin": "ㄉㄥˇ",
    "ja": "待つ",
    "pos": "V"
  },
  {
    "id": "L0-1105",
    "tw": "看",
    "pinyin": "kàn",
    "zhuyin": "ㄎㄢˋ",
    "ja": "見る",
    "pos": "V"
  },
  {
    "id": "L0-1106",
    "tw": "就",
    "pinyin": "jiù",
    "zhuyin": "ㄐㄧㄡˋ",
    "ja": "すぐに、もう",
    "pos": "Adv"
  },
  {
    "id": "L0-1107",
    "tw": "什麼",
    "pinyin": "shénme",
    "zhuyin": "ㄕㄣˊ ㄇㄜ˙",
    "ja": "何",
    "pos": "N"
  },
  {
    "id": "L0-1108",
    "tw": "朋友",
    "pinyin": "péngyǒu",
    "zhuyin": "ㄆㄥˊ ㄧㄡˇ",
    "ja": "友達",
    "pos": "N"
  },
  {
    "id": "L0-1109",
    "tw": "東西",
    "pinyin": "dōngxi",
    "zhuyin": "ㄉㄨㄥ ㄒㄧ˙",
    "ja": "物",
    "pos": "N"
  },
  {
    "id": "L0-1110",
    "tw": "吧",
    "pinyin": "ba",
    "zhuyin": "ㄅㄚ˙",
    "ja": "でしょう、語気の助詞",
    "pos": "Ptc"
  },
  {
    "id": "L0-1111",
    "tw": "呢",
    "pinyin": "ne",
    "zhuyin": "ㄋㄜ˙",
    "ja": "は、語気の助詞",
    "pos": "Ptc"
  },
  {
    "id": "L0-1112",
    "tw": "嗎",
    "pinyin": "ma",
    "zhuyin": "ㄇㄚ˙",
    "ja": "か、疑問の助詞",
    "pos": "Ptc"
  },
  {
    "id": "L0-1113",
    "tw": "找",
    "pinyin": "zhǎo",
    "zhuyin": "ㄓㄠˇ",
    "ja": "探す",
    "pos": "V"
  },
  {
    "id": "L0-1114",
    "tw": "做",
    "pinyin": "zuò",
    "zhuyin": "ㄗㄨㄛˋ",
    "ja": "する、作る",
    "pos": "V"
  },
  {
    "id": "L0-1115",
    "tw": "再見",
    "pinyin": "zàijiàn",
    "zhuyin": "ㄗㄞˋ ㄐㄧㄢˋ",
    "ja": "さようなら",
    "pos": "Vi"
  },
  {
    "id": "L0-1116",
    "tw": "怎麼樣",
    "pinyin": "zěnmeyàng",
    "zhuyin": "ㄗㄣˇ ㄇㄜ˙ ㄧㄤˋ",
    "ja": "どう、いかが",
    "pos": "Vs"
  },
  {
    "id": "L0-1117",
    "tw": "叫",
    "pinyin": "jiào",
    "zhuyin": "ㄐㄧㄠˋ",
    "ja": "と呼ぶ、と言う",
    "pos": "Vst/V"
  },
  {
    "id": "L0-1118",
    "tw": "謝謝",
    "pinyin": "xièxie",
    "zhuyin": "ㄒㄧㄝˋ ㄒㄧㄝ˙",
    "ja": "ありがとう",
    "pos": "Vst"
  },
  {
    "id": "L0-1119",
    "tw": "對不起",
    "pinyin": "duìbùqǐ",
    "zhuyin": "ㄉㄨㄟˋ ㄅㄨˋ ㄑㄧˇ",
    "ja": "ごめんなさい",
    "pos": ""
  },
  {
    "id": "L0-1120",
    "tw": "請問",
    "pinyin": "qǐngwèn",
    "zhuyin": "ㄑㄧㄥˇ ㄨㄣˋ",
    "ja": "お尋ねします",
    "pos": ""
  },
  {
    "id": "L0-1121",
    "tw": "這",
    "pinyin": "zhè",
    "zhuyin": "ㄓㄜˋ",
    "ja": "これ",
    "pos": "Det"
  },
  {
    "id": "L0-1122",
    "tw": "那",
    "pinyin": "nà",
    "zhuyin": "ㄋㄚˋ",
    "ja": "それ、あれ",
    "pos": "Det"
  },
  {
    "id": "L0-1123",
    "tw": "公車",
    "pinyin": "gōnggòngqìchē",
    "zhuyin": "ㄍㄨㄥ ㄍㄨㄥˋ ㄑㄧˋ ㄔㄜ",
    "ja": "バス",
    "pos": "N"
  },
  {
    "id": "L0-1124",
    "tw": "車子",
    "pinyin": "chēzi",
    "zhuyin": "ㄔㄜ ㄗ˙",
    "ja": "車",
    "pos": "N"
  },
  {
    "id": "L0-1125",
    "tw": "到",
    "pinyin": "dào",
    "zhuyin": "ㄉㄠˋ",
    "ja": "到着する、まで",
    "pos": "V"
  },
  {
    "id": "L0-1126",
    "tw": "去",
    "pinyin": "qù",
    "zhuyin": "ㄑㄩˋ",
    "ja": "行く",
    "pos": "V"
  },
  {
    "id": "L0-1127",
    "tw": "回",
    "pinyin": "huí",
    "zhuyin": "ㄏㄨㄟˊ",
    "ja": "帰る",
    "pos": "V"
  },
  {
    "id": "L0-1128",
    "tw": "坐",
    "pinyin": "zuò",
    "zhuyin": "ㄗㄨㄛˋ",
    "ja": "座る、乗る",
    "pos": "Vi"
  },
  {
    "id": "L0-1129",
    "tw": "這裡",
    "pinyin": "zhèlǐ",
    "zhuyin": "ㄓㄜˋ ㄌㄧˇ",
    "ja": "ここ",
    "pos": "N"
  },
  {
    "id": "L0-1130",
    "tw": "那裡",
    "pinyin": "nàlǐ",
    "zhuyin": "ㄋㄚˋ ㄌㄧˇ",
    "ja": "そこ、あそこ",
    "pos": "N"
  },
  {
    "id": "L0-1131",
    "tw": "哪裡",
    "pinyin": "nǎlǐ",
    "zhuyin": "ㄋㄚˇ ㄌㄧˇ",
    "ja": "どこ",
    "pos": "N"
  },
  {
    "id": "L0-1132",
    "tw": "開車",
    "pinyin": "kāichē",
    "zhuyin": "ㄎㄞ ㄔㄜ",
    "ja": "運転する",
    "pos": "V-sep"
  },
  {
    "id": "L0-1133",
    "tw": "錢",
    "pinyin": "qián",
    "zhuyin": "ㄑㄧㄢˊ",
    "ja": "お金",
    "pos": "N"
  },
  {
    "id": "L0-1134",
    "tw": "多少",
    "pinyin": "duōshǎo",
    "zhuyin": "ㄉㄨㄛ ㄕㄠˇ",
    "ja": "どのくらい、いくら",
    "pos": "N"
  },
  {
    "id": "L0-1135",
    "tw": "給",
    "pinyin": "gěi",
    "zhuyin": "ㄍㄟˇ",
    "ja": "あげる、与える",
    "pos": "V"
  },
  {
    "id": "L0-1136",
    "tw": "貴",
    "pinyin": "guì",
    "zhuyin": "ㄍㄨㄟˋ",
    "ja": "高い、値段が高い",
    "pos": "Vs"
  },
  {
    "id": "L0-1137",
    "tw": "便宜",
    "pinyin": "piányí",
    "zhuyin": "ㄆㄧㄢˊ ㄧˊ",
    "ja": "安い",
    "pos": "Vs"
  },
  {
    "id": "L0-1138",
    "tw": "大",
    "pinyin": "dà",
    "zhuyin": "ㄉㄚˋ",
    "ja": "大きい",
    "pos": "Vs"
  },
  {
    "id": "L0-1139",
    "tw": "小",
    "pinyin": "xiǎo",
    "zhuyin": "ㄒㄧㄠˇ",
    "ja": "小さい",
    "pos": "Vs"
  },
  {
    "id": "L0-1140",
    "tw": "難",
    "pinyin": "nán",
    "zhuyin": "ㄋㄢˊ",
    "ja": "難しい",
    "pos": "Vs"
  },
  {
    "id": "L0-1141",
    "tw": "容易",
    "pinyin": "róngyì",
    "zhuyin": "ㄖㄨㄥˊ ㄧˋ",
    "ja": "簡単",
    "pos": "Vs"
  },
  {
    "id": "L0-1142",
    "tw": "有",
    "pinyin": "yǒu",
    "zhuyin": "ㄧㄡˇ",
    "ja": "ある、いる",
    "pos": "Vst"
  },
  {
    "id": "L0-1143",
    "tw": "想",
    "pinyin": "xiǎng",
    "zhuyin": "ㄒㄧㄤˇ",
    "ja": "したい、思う",
    "pos": "Vst"
  },
  {
    "id": "L0-1144",
    "tw": "幾",
    "pinyin": "jǐ",
    "zhuyin": "ㄐㄧˇ",
    "ja": "いくつ",
    "pos": "Det"
  },
  {
    "id": "L0-1145",
    "tw": "塊",
    "pinyin": "kuài",
    "zhuyin": "ㄎㄨㄞˋ",
    "ja": "元、量詞",
    "pos": "M"
  },
  {
    "id": "L0-1146",
    "tw": "位",
    "pinyin": "wèi",
    "zhuyin": "ㄨㄟˋ",
    "ja": "名、人を数える量詞",
    "pos": "M"
  },
  {
    "id": "L0-1147",
    "tw": "飯",
    "pinyin": "fàn",
    "zhuyin": "ㄈㄢˋ",
    "ja": "ご飯",
    "pos": "N"
  },
  {
    "id": "L0-1148",
    "tw": "吃",
    "pinyin": "chī",
    "zhuyin": "ㄔ",
    "ja": "食べる",
    "pos": "V"
  },
  {
    "id": "L0-1149",
    "tw": "請",
    "pinyin": "qǐng",
    "zhuyin": "ㄑㄧㄥˇ",
    "ja": "どうぞ、招く",
    "pos": "V"
  },
  {
    "id": "L0-1150",
    "tw": "也",
    "pinyin": "yě",
    "zhuyin": "ㄧㄝˇ",
    "ja": "も",
    "pos": "Adv"
  },
  {
    "id": "L0-1151",
    "tw": "不",
    "pinyin": "bù",
    "zhuyin": "ㄅㄨˋ",
    "ja": "ない、否定",
    "pos": "Adv"
  },
  {
    "id": "L0-1152",
    "tw": "沒",
    "pinyin": "méi",
    "zhuyin": "ㄇㄟˊ",
    "ja": "ない、過去の否定",
    "pos": "Adv"
  },
  {
    "id": "L0-1153",
    "tw": "都",
    "pinyin": "dōu",
    "zhuyin": "ㄉㄡ",
    "ja": "みんな、全部",
    "pos": "Adv"
  },
  {
    "id": "L0-1154",
    "tw": "只",
    "pinyin": "zhǐ",
    "zhuyin": "ㄓˇ",
    "ja": "だけ",
    "pos": "Adv"
  },
  {
    "id": "L0-1155",
    "tw": "可是",
    "pinyin": "kěshì",
    "zhuyin": "ㄎㄜˇ ㄕˋ",
    "ja": "しかし",
    "pos": "Conj"
  },
  {
    "id": "L0-1156",
    "tw": "還是",
    "pinyin": "háishì",
    "zhuyin": "ㄏㄞˊ ㄕˋ",
    "ja": "それとも、やはり",
    "pos": "Conj"
  },
  {
    "id": "L0-1157",
    "tw": "了",
    "pinyin": "le",
    "zhuyin": "ㄌㄜ˙",
    "ja": "完了の助詞",
    "pos": "Ptc"
  },
  {
    "id": "L0-1158",
    "tw": "得",
    "pinyin": "de",
    "zhuyin": "ㄉㄜ˙",
    "ja": "補語の助詞",
    "pos": "Ptc"
  },
  {
    "id": "L0-1159",
    "tw": "過",
    "pinyin": "guò",
    "zhuyin": "ㄍㄨㄛˋ",
    "ja": "経験の助詞",
    "pos": "Ptc"
  },
  {
    "id": "L0-1160",
    "tw": "沒有",
    "pinyin": "méiyǒu",
    "zhuyin": "ㄇㄟˊ ㄧㄡˇ",
    "ja": "ない",
    "pos": "Ptc"
  }
]
